vitrage_dashboard/__init__.py
vitrage_dashboard/admin_alarms/__init__.py
vitrage_dashboard/admin_alarms/panel.py
vitrage_dashboard/admin_alarms/urls.py
vitrage_dashboard/admin_alarms/views.py
vitrage_dashboard/admin_alarms/templates/adminalarms/index.html
vitrage_dashboard/admin_dashboard/__init__.py
vitrage_dashboard/admin_dashboard/panel.py
vitrage_dashboard/admin_dashboard/urls.py
vitrage_dashboard/admin_dashboard/views.py
vitrage_dashboard/admin_dashboard/templates/admintopology/index.html
vitrage_dashboard/admin_entities/__init__.py
vitrage_dashboard/admin_entities/panel.py
vitrage_dashboard/admin_entities/urls.py
vitrage_dashboard/admin_entities/views.py
vitrage_dashboard/admin_entities/templates/adminentities/index.html
vitrage_dashboard/admin_templates/__init__.py
vitrage_dashboard/admin_templates/panel.py
vitrage_dashboard/admin_templates/urls.py
vitrage_dashboard/admin_templates/views.py
vitrage_dashboard/admin_templates/templates/admintemplates/index.html
vitrage_dashboard/alarms/__init__.py
vitrage_dashboard/alarms/panel.py
vitrage_dashboard/alarms/urls.py
vitrage_dashboard/alarms/views.py
vitrage_dashboard/alarms/templates/alarms/banner.html
vitrage_dashboard/alarms/templates/alarms/index.html
vitrage_dashboard/api/__init__.py
vitrage_dashboard/api/vitrage.py
vitrage_dashboard/api/vitrage_rest_api.py
vitrage_dashboard/dashboard/__init__.py
vitrage_dashboard/dashboard/panel.py
vitrage_dashboard/dashboard/urls.py
vitrage_dashboard/dashboard/views.py
vitrage_dashboard/dashboard/static/app/core/openstack-service-api/vitrage.service.js
vitrage_dashboard/dashboard/static/app/core/openstack-service-api/vitrage.service.spec.js
vitrage_dashboard/dashboard/static/dashboard/project/vitrage.module.js
vitrage_dashboard/dashboard/static/dashboard/project/vitrage.scss
vitrage_dashboard/dashboard/static/dashboard/project/alarmList/alarmList.controller.js
vitrage_dashboard/dashboard/static/dashboard/project/alarmList/alarmList.html
vitrage_dashboard-9.0.0.dist-info/AUTHORS
vitrage_dashboard-9.0.0.dist-info/LICENSE
vitrage_dashboard-9.0.0.dist-info/METADATA
vitrage_dashboard-9.0.0.dist-info/WHEEL
vitrage_dashboard-9.0.0.dist-info/pbr.json
vitrage_dashboard-9.0.0.dist-info/top_level.txt
vitrage_dashboard-9.0.0.dist-info/RECORD
